soda/contracts/check.py
soda/contracts/contract.py
soda/contracts/contract_verification.py
soda/contracts/soda_data_contract_json_schema_1_0_0.json
soda/contracts/impl/consistent_hash_builder.py
soda/contracts/impl/contract_data_source.py
soda/contracts/impl/contract_verification_impl.py
soda/contracts/impl/customized_sodacl_soda_cloud.py
soda/contracts/impl/json_schema_verifier.py
soda/contracts/impl/logs.py
soda/contracts/impl/plugin.py
soda/contracts/impl/soda_cloud.py
soda/contracts/impl/sodacl_log_converter.py
soda/contracts/impl/sql_dialect.py
soda/contracts/impl/variable_resolver.py
soda/contracts/impl/yaml_helper.py
soda_core_contracts-3.5.6.dist-info/METADATA
soda_core_contracts-3.5.6.dist-info/WHEEL
soda_core_contracts-3.5.6.dist-info/top_level.txt
soda_core_contracts-3.5.6.dist-info/RECORD
