Metadata-Version: 2.1
Name: soda-core-contracts
Version: 3.5.6
Requires-Dist: soda-core==3.5.6
Requires-Dist: jsonschema>=4.20.0
